{
  "kind": "collectionType",
  "collectionName": "posts",
  "info": {
    "singularName": "post",
    "pluralName": "posts",
    "displayName": "post",
    "description": ""
  },
  "options": {
    "draftAndPublish": true
  },
  "pluginOptions": {},
  "attributes": {
    "title": {
      "type": "string"
    },
    "date": {
      "type": "date",
      "required": true
    },
    "authors": {
      "type": "relation",
      "relation": "oneToMany",
      "target": "admin::user"
    },
    "cover": {
      "type": "media",
      "multiple": false,
      "required": false,
      "allowedTypes": [
        "images"
      ]
    },
    "content": {
      "type": "richtext"
    },
    "postSeo": {
      "type": "component",
      "repeatable": false,
      "component": "seo.seo-information"
    },
    "slug": {
      "type": "uid",
      "targetField": "title",
      "required": true
    },
    "tags": {
      "type": "relation",
      "relation": "oneToMany",
      "target": "api::tag.tag"
    }
  }
}
